Workbook

Sheet Assumptions
A1: Toddler Companion — Realtime API Cost Model
A2: Edit the BLUE cells. Everything else is a formula.
A4: USAGE
A5: Sessions per day | B5: 2 | E5: Brief targets 15-20 min sessions, designed to end (§2.7)
A6: Minutes per session | B6: 20 | E6: §7 success criterion is 20 min of sustained play
A7: Days per month | B7: 30
A8: Sessions per month | B8: =B5*B7 -> 60
A10: DUTY CYCLE — this is where the design saves you money
A11: Child speech duty cycle (fraction of session mic is open) | B11: 0.35 | E11: Local VAD gates the mic (§3.2). Toddler vocalises a lot but not continuously.
A12: Agent responses per session | B12: 45 | E12: One per child utterance the agent acts on
A13: Agent response length (seconds) | B13: 1.5 | E13: §2.5 caps responses at ~1 sentence / 1-2s. Brevity is a cost lever AND a design principle.
A14: Frames sent per session | B14: 45 | E14: §2.4: 1-2 frames at speech onset, NOT continuous video. Continuous 1fps for 20min = 1,200 frames.
A16: DERIVED — billed audio per session
A17: Child audio minutes billed per session | B17: =B6*B11 -> 7
A18: Agent audio minutes billed per session | B18: =B12*B13/60 -> 1.125
A19: Total active audio minutes (vs 20 min wall-clock) | B19: =B17+B18 -> 8.125 | E19: The gap between this and wall-clock is the whole cost story.
A21: PROVIDER TOKEN MECHANICS
A22: User audio tokens per minute | B22: 600 | E22: OpenAI: 1 token / 100ms of user audio
A23: Assistant audio tokens per minute | B23: 1200 | E23: OpenAI: 1 token / 50ms of assistant audio
A24: Tokens per image frame (low-res) | B24: 85 | E24: Low-detail image. Verify against your frame size.
A26: CONTEXT REPLAY — LARGEST UNCERTAINTY, MEASURE THIS FIRST
A27: Context replay multiplier | B27: 4 | E27: Accumulated conversation is reprocessed per response. 1.0 = no replay. This is a GUESS — instrument it.
A28: Cached input rate (fraction of full price) | B28: 0.25 | E28: Prompt caching discount on replayed context. Verify against your provider's current rate.
A30: COMMERCIAL TARGET
A31: Target retail price per month ($) | B31: 10 | E31: What a parent plausibly pays for a kids' app
A32: Target gross margin | B32: 0.7
A33: COGS budget per month ($) | B33: =B31*(1-B32) -> 3 | E33: Everything below this line has to fit inside this number.
A35: PRICING ($ per 1M tokens, verified 2026-09-07)
A36: Model | B36: Audio in | C36: Audio out
A37: gpt-realtime-2.1 | B37: 32 | C37: 64 | E37: Flagship. Overkill for a one-sentence sportscaster.
A38: gpt-realtime-2.1-mini | B38: 10 | C38: 20 | E38: RECOMMENDED for prototype — see docs/provider-matrix.md
A39: gemini-3.1-flash-live | B39: 3 | C39: 12 | E39: CHEAPEST BUT PROHIBITED: terms bar services likely accessed by under-18s.

Sheet Model
A1: Cost per session and per month, by model
A2: All figures flow from the Assumptions tab.
A4: Metric | B4: gpt-realtime-2.1 | C4: gpt-realtime-2.1-mini | D4: gemini-3.1-flash-live
A5: Audio in — $/1M tokens | B5: =Assumptions!B37 -> 32 | C5: =Assumptions!B38 -> 10 | D5: =Assumptions!B39 -> 3
A6: Audio out — $/1M tokens | B6: =Assumptions!C37 -> 64 | C6: =Assumptions!C38 -> 20 | D6: =Assumptions!C39 -> 12
A8: TOKENS PER SESSION
A9: Input audio tokens | B9: =Assumptions!$B$17*Assumptions!$B$22 -> 4200 | C9: =Assumptions!$B$17*Assumptions!$B$22 -> 4200 | D9: =Assumptions!$B$17*Assumptions!$B$22 -> 4200
A10: Frame tokens | B10: =Assumptions!$B$14*Assumptions!$B$24 -> 3825 | C10: =Assumptions!$B$14*Assumptions!$B$24 -> 3825 | D10: =Assumptions!$B$14*Assumptions!$B$24 -> 3825 | E10: Only 45 frames. Continuous video would be ~26x this.
A11: Output audio tokens | B11: =Assumptions!$B$18*Assumptions!$B$23 -> 1350 | C11: =Assumptions!$B$18*Assumptions!$B$23 -> 1350 | D11: =Assumptions!$B$18*Assumptions!$B$23 -> 1350
A12: Replayed context tokens (cached) | B12: =(B9+B10)*(Assumptions!$B$27-1) -> 24075 | C12: =(C9+C10)*(Assumptions!$B$27-1) -> 24075 | D12: =(D9+D10)*(Assumptions!$B$27-1) -> 24075
A14: COST PER SESSION
A15: Fresh input | B15: =(B9+B10)/1000000*B5 -> 0.2568 | C15: =(C9+C10)/1000000*C5 -> 0.08025 | D15: =(D9+D10)/1000000*D5 -> 0.024075
A16: Replayed input (cached) | B16: =B12/1000000*B5*Assumptions!$B$28 -> 0.1926 | C16: =C12/1000000*C5*Assumptions!$B$28 -> 0.0601875 | D16: =D12/1000000*D5*Assumptions!$B$28 -> 0.01805625
A17: Output | B17: =B11/1000000*B6 -> 0.0864 | C17: =C11/1000000*C6 -> 0.027 | D17: =D11/1000000*D6 -> 0.0162
A18: Total per session | B18: =SUM(B15:B17) -> 0.5358 | C18: =SUM(C15:C17) -> 0.1674375 | D18: =SUM(D15:D17) -> 0.05833125
A20: COST PER MONTH
A21: Cost per month | B21: =B18*Assumptions!$B$8 -> 32.148 | C21: =C18*Assumptions!$B$8 -> 10.04625 | D21: =D18*Assumptions!$B$8 -> 3.499875
A22: COGS budget per month | B22: =Assumptions!$B$33 -> 3 | C22: =Assumptions!$B$33 -> 3 | D22: =Assumptions!$B$33 -> 3
A23: Multiple of budget | B23: =IF(B22=0,"n/a",B21/B22) -> 10.716 | C23: =IF(C22=0,"n/a",C21/C22) -> 3.34875 | D23: =IF(D22=0,"n/a",D21/D22) -> 1.166625
A24: Verdict | B24: =IF(B21<=B22,"WITHIN BUDGET","OVER BUDGET") -> OVER BUDGET | C24: =IF(C21<=C22,"WITHIN BUDGET","OVER BUDGET") -> OVER BUDGET | D24: =IF(D21<=D22,"WITHIN BUDGET","OVER BUDGET") -> OVER BUDGET
A25: Break-even retail price ($/mo) | B25: =IF(Assumptions!$B$32>=1,"n/a",B21/(1-Assumptions!$B$32)) -> 107.16 | C25: =IF(Assumptions!$B$32>=1,"n/a",C21/(1-Assumptions!$B$32)) -> 33.4875 | D25: =IF(Assumptions!$B$32>=1,"n/a",D21/(1-Assumptions!$B$32)) -> 11.66625 | E25: What you'd have to charge to hit target margin.
A27: NOTE: gemini-3.1-flash-live is shown for comparison only. Its terms prohibit
A28: use in a service likely to be accessed by under-18s. See docs/provider-matrix.md.

Sheet Sensitivity
A1: Monthly cost — gpt-realtime-2.1-mini
A2: Duty cycle (down) vs sessions per day (across). Yellow = within COGS budget.
A4: Duty cycle \ sessions/day | B4: 1 | C4: 2 | D4: 3 | E4: 4 | F4: 5
A5: 0.15 | B5: =((Assumptions!$B$6*$A5*Assumptions!$B$22 + Assumptions!$B$14*Assumptions!$B$24)/1000000*Assumptions!$B$38+((Assumptions!$B$6*$A5*Assumptions!$B$22 + Assumptions!$B$14*Assumptions!$B$24)*(Assumptions!$B$27-1))/1000000*Assumptions!$B$38*Assumptions!$B$28+(Assumptions!$B$18*Assumptions!$B$23)/1000000*Assumptions!$C$38)*1*Assumptions!$B$7 -> 3.763125 | C5: =((Assumptions!$B$6*$A5*Assumptions!$B$22 + Assumptions!$B$14*Assumptions!$B$24)/1000000*Assumptions!$B$38+((Assumptions!$B$6*$A5*Assumptions!$B$22 + Assumptions!$B$14*Assumptions!$B$24)*(Assumptions!$B$27-1))/1000000*Assumptions!$B$38*Assumptions!$B$28+(Assumptions!$B$18*Assumptions!$B$23)/1000000*Assumptions!$C$38)*2*Assumptions!$B$7 -> 7.52625 | D5: =((Assumptions!$B$6*$A5*Assumptions!$B$22 + Assumptions!$B$14*Assumptions!$B$24)/1000000*Assumptions!$B$38+((Assumptions!$B$6*$A5*Assumptions!$B$22 + Assumptions!$B$14*Assumptions!$B$24)*(Assumptions!$B$27-1))/1000000*Assumptions!$B$38*Assumptions!$B$28+(Assumptions!$B$18*Assumptions!$B$23)/1000000*Assumptions!$C$38)*3*Assumptions!$B$7 -> 11.289375 | E5: =((Assumptions!$B$6*$A5*Assumptions!$B$22 + Assumptions!$B$14*Assumptions!$B$24)/1000000*Assumptions!$B$38+((Assumptions!$B$6*$A5*Assumptions!$B$22 + Assumptions!$B$14*Assumptions!$B$24)*(Assumptions!$B$27-1))/1000000*Assumptions!$B$38*Assumptions!$B$28+(Assumptions!$B$18*Assumptions!$B$23)/1000000*Assumptions!$C$38)*4*Assumptions!$B$7 -> 15.0525 | F5: =((Assumptions!$B$6*$A5*Assumptions!$B$22 + Assumptions!$B$14*Assumptions!$B$24)/1000000*Assumptions!$B$38+((Assumptions!$B$6*$A5*Assumptions!$B$22 + Assumptions!$B$14*Assumptions!$B$24)*(Assumptions!$B$27-1))/1000000*Assumptions!$B$38*Assumptions!$B$28+(Assumptions!$B$18*Assumptions!$B$23)/1000000*Assumptions!$C$38)*5*Assumptions!$B$7 -> 18.815625
A6: 0.25 | B6: =((Assumptions!$B$6*$A6*Assumptions!$B$22 + Assumptions!$B$14*Assumptions!$B$24)/1000000*Assumptions!$B$38+((Assumptions!$B$6*$A6*Assumptions!$B$22 + Assumptions!$B$14*Assumptions!$B$24)*(Assumptions!$B$27-1))/1000000*Assumptions!$B$38*Assumptions!$B$28+(Assumptions!$B$18*Assumptions!$B$23)/1000000*Assumptions!$C$38)*1*Assumptions!$B$7 -> 4.393125 | C6: =((Assumptions!$B$6*$A6*Assumptions!$B$22 + Assumptions!$B$14*Assumptions!$B$24)/1000000*Assumptions!$B$38+((Assumptions!$B$6*$A6*Assumptions!$B$22 + Assumptions!$B$14*Assumptions!$B$24)*(Assumptions!$B$27-1))/1000000*Assumptions!$B$38*Assumptions!$B$28+(Assumptions!$B$18*Assumptions!$B$23)/1000000*Assumptions!$C$38)*2*Assumptions!$B$7 -> 8.78625 | D6: =((Assumptions!$B$6*$A6*Assumptions!$B$22 + Assumptions!$B$14*Assumptions!$B$24)/1000000*Assumptions!$B$38+((Assumptions!$B$6*$A6*Assumptions!$B$22 + Assumptions!$B$14*Assumptions!$B$24)*(Assumptions!$B$27-1))/1000000*Assumptions!$B$38*Assumptions!$B$28+(Assumptions!$B$18*Assumptions!$B$23)/1000000*Assumptions!$C$38)*3*Assumptions!$B$7 -> 13.179375 | E6: =((Assumptions!$B$6*$A6*Assumptions!$B$22 + Assumptions!$B$14*Assumptions!$B$24)/1000000*Assumptions!$B$38+((Assumptions!$B$6*$A6*Assumptions!$B$22 + Assumptions!$B$14*Assumptions!$B$24)*(Assumptions!$B$27-1))/1000000*Assumptions!$B$38*Assumptions!$B$28+(Assumptions!$B$18*Assumptions!$B$23)/1000000*Assumptions!$C$38)*4*Assumptions!$B$7 -> 17.5725 | F6: =((Assumptions!$B$6*$A6*Assumptions!$B$22 + Assumptions!$B$14*Assumptions!$B$24)/1000000*Assumptions!$B$38+((Assumptions!$B$6*$A6*Assumptions!$B$22 + Assumptions!$B$14*Assumptions!$B$24)*(Assumptions!$B$27-1))/1000000*Assumptions!$B$38*Assumptions!$B$28+(Assumptions!$B$18*Assumptions!$B$23)/1000000*Assumptions!$C$38)*5*Assumptions!$B$7 -> 21.965625
A7: 0.35 | B7: =((Assumptions!$B$6*$A7*Assumptions!$B$22 + Assumptions!$B$14*Assumptions!$B$24)/1000000*Assumptions!$B$38+((Assumptions!$B$6*$A7*Assumptions!$B$22 + Assumptions!$B$14*Assumptions!$B$24)*(Assumptions!$B$27-1))/1000000*Assumptions!$B$38*Assumptions!$B$28+(Assumptions!$B$18*Assumptions!$B$23)/1000000*Assumptions!$C$38)*1*Assumptions!$B$7 -> 5.023125 | C7: =((Assumptions!$B$6*$A7*Assumptions!$B$22 + Assumptions!$B$14*Assumptions!$B$24)/1000000*Assumptions!$B$38+((Assumptions!$B$6*$A7*Assumptions!$B$22 + Assumptions!$B$14*Assumptions!$B$24)*(Assumptions!$B$27-1))/1000000*Assumptions!$B$38*Assumptions!$B$28+(Assumptions!$B$18*Assumptions!$B$23)/1000000*Assumptions!$C$38)*2*Assumptions!$B$7 -> 10.04625 | D7: =((Assumptions!$B$6*$A7*Assumptions!$B$22 + Assumptions!$B$14*Assumptions!$B$24)/1000000*Assumptions!$B$38+((Assumptions!$B$6*$A7*Assumptions!$B$22 + Assumptions!$B$14*Assumptions!$B$24)*(Assumptions!$B$27-1))/1000000*Assumptions!$B$38*Assumptions!$B$28+(Assumptions!$B$18*Assumptions!$B$23)/1000000*Assumptions!$C$38)*3*Assumptions!$B$7 -> 15.069375 | E7: =((Assumptions!$B$6*$A7*Assumptions!$B$22 + Assumptions!$B$14*Assumptions!$B$24)/1000000*Assumptions!$B$38+((Assumptions!$B$6*$A7*Assumptions!$B$22 + Assumptions!$B$14*Assumptions!$B$24)*(Assumptions!$B$27-1))/1000000*Assumptions!$B$38*Assumptions!$B$28+(Assumptions!$B$18*Assumptions!$B$23)/1000000*Assumptions!$C$38)*4*Assumptions!$B$7 -> 20.0925 | F7: =((Assumptions!$B$6*$A7*Assumptions!$B$22 + Assumptions!$B$14*Assumptions!$B$24)/1000000*Assumptions!$B$38+((Assumptions!$B$6*$A7*Assumptions!$B$22 + Assumptions!$B$14*Assumptions!$B$24)*(Assumptions!$B$27-1))/1000000*Assumptions!$B$38*Assumptions!$B$28+(Assumptions!$B$18*Assumptions!$B$23)/1000000*Assumptions!$C$38)*5*Assumptions!$B$7 -> 25.115625
A8: 0.5 | B8: =((Assumptions!$B$6*$A8*Assumptions!$B$22 + Assumptions!$B$14*Assumptions!$B$24)/1000000*Assumptions!$B$38+((Assumptions!$B$6*$A8*Assumptions!$B$22 + Assumptions!$B$14*Assumptions!$B$24)*(Assumptions!$B$27-1))/1000000*Assumptions!$B$38*Assumptions!$B$28+(Assumptions!$B$18*Assumptions!$B$23)/1000000*Assumptions!$C$38)*1*Assumptions!$B$7 -> 5.968125 | C8: =((Assumptions!$B$6*$A8*Assumptions!$B$22 + Assumptions!$B$14*Assumptions!$B$24)/1000000*Assumptions!$B$38+((Assumptions!$B$6*$A8*Assumptions!$B$22 + Assumptions!$B$14*Assumptions!$B$24)*(Assumptions!$B$27-1))/1000000*Assumptions!$B$38*Assumptions!$B$28+(Assumptions!$B$18*Assumptions!$B$23)/1000000*Assumptions!$C$38)*2*Assumptions!$B$7 -> 11.93625 | D8: =((Assumptions!$B$6*$A8*Assumptions!$B$22 + Assumptions!$B$14*Assumptions!$B$24)/1000000*Assumptions!$B$38+((Assumptions!$B$6*$A8*Assumptions!$B$22 + Assumptions!$B$14*Assumptions!$B$24)*(Assumptions!$B$27-1))/1000000*Assumptions!$B$38*Assumptions!$B$28+(Assumptions!$B$18*Assumptions!$B$23)/1000000*Assumptions!$C$38)*3*Assumptions!$B$7 -> 17.904375 | E8: =((Assumptions!$B$6*$A8*Assumptions!$B$22 + Assumptions!$B$14*Assumptions!$B$24)/1000000*Assumptions!$B$38+((Assumptions!$B$6*$A8*Assumptions!$B$22 + Assumptions!$B$14*Assumptions!$B$24)*(Assumptions!$B$27-1))/1000000*Assumptions!$B$38*Assumptions!$B$28+(Assumptions!$B$18*Assumptions!$B$23)/1000000*Assumptions!$C$38)*4*Assumptions!$B$7 -> 23.8725 | F8: =((Assumptions!$B$6*$A8*Assumptions!$B$22 + Assumptions!$B$14*Assumptions!$B$24)/1000000*Assumptions!$B$38+((Assumptions!$B$6*$A8*Assumptions!$B$22 + Assumptions!$B$14*Assumptions!$B$24)*(Assumptions!$B$27-1))/1000000*Assumptions!$B$38*Assumptions!$B$28+(Assumptions!$B$18*Assumptions!$B$23)/1000000*Assumptions!$C$38)*5*Assumptions!$B$7 -> 29.840625
A9: 0.7 | B9: =((Assumptions!$B$6*$A9*Assumptions!$B$22 + Assumptions!$B$14*Assumptions!$B$24)/1000000*Assumptions!$B$38+((Assumptions!$B$6*$A9*Assumptions!$B$22 + Assumptions!$B$14*Assumptions!$B$24)*(Assumptions!$B$27-1))/1000000*Assumptions!$B$38*Assumptions!$B$28+(Assumptions!$B$18*Assumptions!$B$23)/1000000*Assumptions!$C$38)*1*Assumptions!$B$7 -> 7.228125 | C9: =((Assumptions!$B$6*$A9*Assumptions!$B$22 + Assumptions!$B$14*Assumptions!$B$24)/1000000*Assumptions!$B$38+((Assumptions!$B$6*$A9*Assumptions!$B$22 + Assumptions!$B$14*Assumptions!$B$24)*(Assumptions!$B$27-1))/1000000*Assumptions!$B$38*Assumptions!$B$28+(Assumptions!$B$18*Assumptions!$B$23)/1000000*Assumptions!$C$38)*2*Assumptions!$B$7 -> 14.45625 | D9: =((Assumptions!$B$6*$A9*Assumptions!$B$22 + Assumptions!$B$14*Assumptions!$B$24)/1000000*Assumptions!$B$38+((Assumptions!$B$6*$A9*Assumptions!$B$22 + Assumptions!$B$14*Assumptions!$B$24)*(Assumptions!$B$27-1))/1000000*Assumptions!$B$38*Assumptions!$B$28+(Assumptions!$B$18*Assumptions!$B$23)/1000000*Assumptions!$C$38)*3*Assumptions!$B$7 -> 21.684375 | E9: =((Assumptions!$B$6*$A9*Assumptions!$B$22 + Assumptions!$B$14*Assumptions!$B$24)/1000000*Assumptions!$B$38+((Assumptions!$B$6*$A9*Assumptions!$B$22 + Assumptions!$B$14*Assumptions!$B$24)*(Assumptions!$B$27-1))/1000000*Assumptions!$B$38*Assumptions!$B$28+(Assumptions!$B$18*Assumptions!$B$23)/1000000*Assumptions!$C$38)*4*Assumptions!$B$7 -> 28.9125 | F9: =((Assumptions!$B$6*$A9*Assumptions!$B$22 + Assumptions!$B$14*Assumptions!$B$24)/1000000*Assumptions!$B$38+((Assumptions!$B$6*$A9*Assumptions!$B$22 + Assumptions!$B$14*Assumptions!$B$24)*(Assumptions!$B$27-1))/1000000*Assumptions!$B$38*Assumptions!$B$28+(Assumptions!$B$18*Assumptions!$B$23)/1000000*Assumptions!$C$38)*5*Assumptions!$B$7 -> 36.140625
A11: COGS budget per month | B11: =Assumptions!$B$33 -> 3
A13: Read this as: which cells fall under the budget in B11.
